LICENSE
MANIFEST.in
README.md
setup.py
mkdocs_img2fig_plugin_with_icons.egg-info/PKG-INFO
mkdocs_img2fig_plugin_with_icons.egg-info/SOURCES.txt
mkdocs_img2fig_plugin_with_icons.egg-info/dependency_links.txt
mkdocs_img2fig_plugin_with_icons.egg-info/entry_points.txt
mkdocs_img2fig_plugin_with_icons.egg-info/requires.txt
mkdocs_img2fig_plugin_with_icons.egg-info/top_level.txt
src/__init__.py
src/plugin.py