Metadata-Version: 2.1
Name: mkdocs-img2fig-plugin-with-icons
Version: 0.0.1
Summary: A MkDocs plugin that converts markdown encoded images into <figure> elements.
Home-page: https://github.com/stuebersystems/mkdocs-img2fig-plugin-with-icons
Author: Antonio Cambule
Author-email: antonio.cambule@stueber.de
License: MIT
Keywords: mkdocs python markdown icons
Platform: UNKNOWN
Requires-Python: >=3.5
License-File: LICENSE
